pyglobalsearch-0.4.0.dist-info/METADATA
pyglobalsearch-0.4.0.dist-info/WHEEL
pyglobalsearch.libs/libgcc_s-0366c7ba.so.1
pyglobalsearch/__init__.py
pyglobalsearch/__init__.pyi
pyglobalsearch/py.typed
pyglobalsearch/pyglobalsearch.cpython-310-arm-linux-gnueabihf.so
pyglobalsearch-0.4.0.dist-info/RECORD
