Metadata-Version: 2.4
Name: pyglobalsearch
Version: 0.4.0
Classifier: Programming Language :: Rust
Classifier: Programming Language :: Python :: Implementation :: CPython
Classifier: Programming Language :: Python :: Implementation :: PyPy
Classifier: Intended Audience :: Science/Research
Classifier: Topic :: Scientific/Engineering
Classifier: Topic :: Scientific/Engineering :: Mathematics
Classifier: License :: OSI Approved :: MIT License
Requires-Dist: numpy>=1.24.4
Requires-Dist: pytest>=8.3.5 ; extra == 'dev'
Requires-Dist: ruff>=0.9.9 ; extra == 'dev'
Provides-Extra: dev
Summary: This package provides a Python interface to Rust's globalsearch crate. globalsearch is a multistart framework for global optimization with scatter search and local NLP solvers written in Rust.
Keywords: optimization,math,science
Author-email: Germán Martín Heim <german.martin.heim@gmail.com>
License-Expression: MIT
Requires-Python: >=3.8
Project-URL: Homepage, https://germanheim.github.io/globalsearch-rs-website/
Project-URL: Documentation, https://germanheim.github.io/pyglobalsearch-website/api.html
Project-URL: Repository, https://github.com/GermanHeim/globalsearch-rs
Project-URL: Changelog, https://github.com/GermanHeim/globalsearch-rs/releases
